Metadata-Version: 2.1
Name: django-stackstore-model
Version: 0.1
Summary: Django stackstore model
Home-page: https://github.com/salexkidd/django-stackstore-model
Author: salexkidd
Author-email: salexkidd@gmail.com
License: UNKNOWN
Keywords: django,model,versioning
Platform: UNKNOWN
Classifier: Development Status :: 5 - Production/Stable
Classifier: Environment :: Web Environment
Classifier: Framework :: Django
Classifier: Intended Audience :: Developers
Classifier: License :: OSI Approved :: MIT License
Classifier: Operating System :: OS Independent
Classifier: Programming Language :: Python
Classifier: Programming Language :: Python :: 3
Classifier: Topic :: Internet :: WWW/HTTP
Classifier: Topic :: Internet :: WWW/HTTP :: Dynamic Content
